{"nationality": {"nationality_acronym": "USA", "nationality_href": "/wiki/United_States", "nationality_title": "United States", "nationality_flag": "https://static.wikia.nocookie.net/f1wikia/images/a/a4/Flag_of_the_United_States.svg/revision/latest?cb=20081117192736"}, "name": "Doc Shanebrook", "id": "Doc_Shanebrook", "image": false, "birth_date": "1907-01-26", "death_date": "1976-08-25", "status": "Deceased", "total_seasons": 2, "seasons_years": [1951, 1952], "titles": "0", "races": "2 (0 starts)", "poles": "0", "wins": "0", "podiums": "0", "fastestlaps": "0", "points": "0", "introduction": "Beuford \"Doc\" Shanebrook (born 26 January 1907 and died 25 August 1976) was an American racing driver who attempted to qualify for the 1951 and 1952 Indianapolis 500, although he was unsuccessful in doing so. A welder by profession, Shanebrook earned the nickname \"Doc\" for his ability to doctor or modify his car."}