{"nationality": {"nationality_acronym": "POL", "nationality_href": "/wiki/Poland", "nationality_title": "Poland", "nationality_flag": "https://static.wikia.nocookie.net/f1wikia/images/1/12/Flag_of_Poland.svg/revision/latest?cb=20081106193134"}, "name": "Robert Kubica", "id": "Robert_Kubica", "image": "https://static.wikia.nocookie.net/f1wikia/images/8/89/Rob_kub.png/revision/latest?cb=20210928071342", "birth_date": "1984-12-07", "death_date": false, "status": "Competing in WEC", "total_seasons": 7, "seasons_years": [2006, 2007, 2008, 2009, 2010, 2019, 2021], "titles": "0", "races": "99 (99 starts)", "poles": "1", "wins": "1", "podiums": "12", "fastestlaps": "1", "points": "274", "introduction": "Robert Jzef Kubica (born 7 December 1984 in Krakw, Poland) is Polish racing driver who currently serves as the Reserve Driver for Alfa Romeo.  Having made his dbut in 2006, Kubica has driven for BMWSauber, Renault and Williams in a career that was interrupted by a serious rallying accident in 2011.  He is the only Polish driver to have competed in Formula One, and he has won one race, the 2008 Canadian Grand Prix."}