{"nationality": {"nationality_acronym": "RUS", "nationality_href": "/wiki/Russia", "nationality_title": "Russia", "nationality_flag": "https://static.wikia.nocookie.net/f1wikia/images/f/f3/Flag_of_Russia.svg/revision/latest?cb=20120124165927"}, "name": "Artem Markelov", "id": "Artem_Markelov", "image": false, "birth_date": "1994-09-10", "death_date": false, "status": "Test driver", "total_seasons": 0, "seasons_years": false, "titles": 0, "races": 0, "poles": 0, "wins": 0, "podiums": 0, "fastestlaps": "0", "points": 0, "introduction": "", "titles_percentage": 0, "poles_percentage": 0, "wins_percentage": 0, "podiums_percentage": 0}