{"nationality": {"nationality_acronym": "USA", "nationality_href": "/wiki/United_States", "nationality_title": "United States", "nationality_flag": "https://static.wikia.nocookie.net/f1wikia/images/a/a4/Flag_of_the_United_States.svg/revision/latest?cb=20081117192736"}, "name": "Russ Klar", "id": "Russ_Klar", "image": false, "birth_date": "1914-04-27", "death_date": "2005-02-16", "status": "Deceased", "total_seasons": 0, "seasons_years": [], "titles": 0, "races": 0, "poles": 0, "wins": 0, "podiums": 0, "fastestlaps": "0", "points": 0, "introduction": "Russell V. Klar (April 27, 1914 - February 16, 2005) was a United States driver who entered one Formula One race for Schroeder-Offenhauser in 1955, the 1955 Indianapolis 500, but failed to qualify.", "titles_percentage": 0, "poles_percentage": 0, "wins_percentage": 0, "podiums_percentage": 0, "seasons_results": {}}