{"constructorId": "hesketh", "url": "http://en.wikipedia.org/wiki/Hesketh_Racing", "name": "Hesketh", "nationality": "British", "titles": 0, "wins": 1, "podiums": 7, "image": "", "seasons_results": {"1974": {"title": 0, "wins": 0, "podiums": 3, "pilots_wins": {"James_Hunt": 0, "Ian_Scheckter": 0}, "pilots_podiums": {"James_Hunt": 3, "Ian_Scheckter": 0}}, "1975": {"title": 0, "wins": 1, "podiums": 4, "pilots_wins": {"James_Hunt": 1, "Alan_Jones": 0, "Torsten_Palm": 0, "Harald_Ertl": 0, "Brett_Lunger": 0}, "pilots_podiums": {"James_Hunt": 4, "Alan_Jones": 0, "Torsten_Palm": 0, "Harald_Ertl": 0, "Brett_Lunger": 0}}, "1976": {"title": 0, "wins": 0, "podiums": 0, "pilots_wins": {"Harald_Ertl": 0, "Guy_Edwards": 0, "Rolf_Stommelen": 0, "Alex_Ribeiro": 0}, "pilots_podiums": {"Harald_Ertl": 0, "Guy_Edwards": 0, "Rolf_Stommelen": 0, "Alex_Ribeiro": 0}}, "1977": {"title": 0, "wins": 0, "podiums": 0, "pilots_wins": {"Rupert_Keegan": 0, "Harald_Ertl": 0, "Hector_Rebaque": 0, "Ian_Ashley": 0}, "pilots_podiums": {"Rupert_Keegan": 0, "Harald_Ertl": 0, "Hector_Rebaque": 0, "Ian_Ashley": 0}}, "1978": {"title": 0, "wins": 0, "podiums": 0, "pilots_wins": {"Divina_Galica": 0, "Eddie_Cheever": 0, "Derek_Daly": 0}, "pilots_podiums": {"Divina_Galica": 0, "Eddie_Cheever": 0, "Derek_Daly": 0}}}}