{"constructorId": "vanwall", "url": "http://en.wikipedia.org/wiki/Vanwall", "name": "Vanwall", "nationality": "British", "titles": 1, "wins": 10, "podiums": 14, "image": "", "seasons_results": {"1954": {"title": 0, "wins": 0, "podiums": 0, "pilots_wins": {}, "pilots_podiums": {}}, "1955": {"title": 0, "wins": 0, "podiums": 0, "pilots_wins": {}, "pilots_podiums": {}}, "1956": {"title": 0, "wins": 0, "podiums": 0, "pilots_wins": {}, "pilots_podiums": {}}, "1957": {"title": 0, "wins": 4, "podiums": 5, "pilots_wins": {"Tony_Brooks": 1, "Stirling_Moss": 3}, "pilots_podiums": {"Tony_Brooks": 2, "Stirling_Moss": 3}}, "1958": {"title": 1, "wins": 6, "podiums": 9, "pilots_wins": {"Stirling_Moss": 3, "Tony_Brooks": 3}, "pilots_podiums": {"Stirling_Moss": 4, "Tony_Brooks": 3, "Stuart_Lewis-Evans": 2}}, "1959": {"title": 0, "wins": 0, "podiums": 0, "pilots_wins": {}, "pilots_podiums": {}}, "1960": {"title": 0, "wins": 0, "podiums": 0, "pilots_wins": {}, "pilots_podiums": {}}}}