{"nationality": {"nationality_acronym": "NZL", "nationality_href": "/wiki/New_Zealand", "nationality_title": "New Zealand", "nationality_flag": "https://static.wikia.nocookie.net/f1wikia/images/3/3e/Flag_of_New_Zealand.svg/revision/latest?cb=20081201184315"}, "name": "Chris Amon", "id": "Chris_Amon", "image": "https://static.wikia.nocookie.net/f1wikia/images/e/e5/Chris_Amon.jpg/revision/latest?cb=20140402202911", "birth_date": "1943-07-20", "death_date": "2016-08-03", "status": "Deceased", "total_seasons": 14, "seasons_years": [1963, 1964, 1965, 1966, 1967, 1968, 1969, 1970, 1971, 1972, 1973, 1974, 1975, 1976], "titles": "0", "races": "120 (95 starts)", "poles": "5", "wins": "0", "podiums": "11", "fastestlaps": "3", "points": "83", "introduction": "Christopher Arthur \"Chris\" Amon MBE (AY-mon; born 20th July, 1943 in Bulls, New Zealand - died 3rd August, 2016[1]) was a former motor racing driver who competed in Formula One between 1963 and 1976. Amon was labelled as one of the best F1 drivers never to win a race. ", "titles_percentage": 0.0, "poles_percentage": 4.17, "wins_percentage": 0.0, "podiums_percentage": 9.17}