{"nationality": {"nationality_acronym": "BEL", "nationality_href": "/wiki/Belgium", "nationality_title": "Belgium", "nationality_flag": "https://static.wikia.nocookie.net/f1wikia/images/6/65/Flag_of_Belgium.svg/revision/latest?cb=20211030054815"}, "name": "Lucien Bianchi", "id": "Lucien_Bianchi", "image": false, "birth_date": "1934-11-10", "death_date": "1969-03-30", "status": "Deceased (Test crash)", "total_seasons": 7, "seasons_years": [1959, 1960, 1961, 1962, 1963, 1965, 1968], "titles": "0", "races": "21 (17 starts)", "poles": "0", "wins": "0", "podiums": "1", "fastestlaps": "0", "points": "6", "introduction": "Lucien Bianchi (bee-AN-key; born as Luciano Bianchi, on November 10, 1934 in Milan, Lombardy, Italy  died March 30, 1969 at the Circuit de la Sarthe, Le Mans, Sarthe, Pays de la Loire, France) was a Belgian racing driver who drove in Formula One.", "titles_percentage": 0.0, "poles_percentage": 0.0, "wins_percentage": 0.0, "podiums_percentage": 4.76, "seasons_results": {"1959": {"title": 0, "races": 1, "wins": 0, "points": 0, "poles": 0, "podiums": 0}, "1960": {"title": 0, "races": 6, "wins": 0, "points": 1.0, "poles": 0, "podiums": 0}, "1961": {"title": 0, "races": 4, "wins": 0, "points": 0, "poles": 0, "podiums": 0}, "1962": {"title": 0, "races": 7, "wins": 0, "points": 0.0, "poles": 0, "podiums": 0}, "1963": {"title": 0, "races": 6, "wins": 0, "points": 0, "poles": 0, "podiums": 0}, "1965": {"title": 0, "races": 8, "wins": 0, "points": 0.0, "poles": 0, "podiums": 0}, "1968": {"title": 0, "races": 10, "wins": 0, "points": 5.0, "poles": 0, "podiums": 0}}}