{"nationality": {"nationality_acronym": "BRA", "nationality_href": "/wiki/Brazil", "nationality_title": "Brazil", "nationality_flag": "https://static.wikia.nocookie.net/f1wikia/images/0/05/Flag_of_Brazil.svg/revision/latest?cb=20081106192246"}, "name": "Luiz-Pereira Bueno", "id": "Luiz_Bueno", "image": "https://static.wikia.nocookie.net/f1wikia/images/a/a7/Luiz_Bueno.jpg/revision/latest/scale-to-width-down/350?cb=20190324185222", "birth_date": "1937-01-16", "death_date": "2011-02-08", "status": "Deceased", "total_seasons": 2, "seasons_years": [1972, 1973], "titles": "0", "races": "1 (1 starts)", "poles": "0", "wins": "0", "podiums": "0", "fastestlaps": "0", "points": "0", "introduction": "Luiz-Pereira Bueno (born 16 January 1937 and died 8 February 2011) was a Brazilian Formula One driver who raced in the 1973 Brazilian Grand Prix with Surtees. He also finished 6th at the non-championship 1972 Brazilian Grand Prix.", "titles_percentage": 0.0, "poles_percentage": 0.0, "wins_percentage": 0.0, "podiums_percentage": 0.0}