{"nationality": {"nationality_acronym": "JPN", "nationality_href": "/wiki/Japan", "nationality_title": "Japan", "nationality_flag": "https://static.wikia.nocookie.net/f1wikia/images/9/9e/Flag_of_Japan.svg/revision/latest?cb=20081106193823"}, "name": "Masami Kuwashima", "id": "Masami_Kuwashima", "image": "https://static.wikia.nocookie.net/f1wikia/images/0/0b/Masami_Kuwashima.png/revision/latest/scale-to-width-down/350?cb=20180422210154", "birth_date": "1950-09-14", "death_date": false, "status": false, "total_seasons": 1, "seasons_years": [1976], "titles": "0", "races": "1 (0 starts)", "poles": "0", "wins": "0", "podiums": "0", "fastestlaps": "0", "points": "0", "introduction": "", "titles_percentage": 0.0, "poles_percentage": 0.0, "wins_percentage": 0.0, "podiums_percentage": 0.0}