{"nationality": {"nationality_acronym": "GER", "nationality_href": "/wiki/Germany", "nationality_title": "Germany", "nationality_flag": "https://static.wikia.nocookie.net/f1wikia/images/b/ba/Flag_of_Germany.svg/revision/latest?cb=20081106192532"}, "name": "Oswald Karch", "id": "Oswald_Karch", "image": false, "birth_date": "1917-03-06", "death_date": "2009-01-28", "status": "Deceased", "total_seasons": 1, "seasons_years": [1953], "titles": "0", "races": "1 (1 starts)", "poles": "0", "wins": "0", "podiums": "0", "fastestlaps": "0", "points": "0", "introduction": "Oswald Karch (born 6 March 1917 and died 28 January 2009) was a German racing driver who primarily raced in Formula Two races within Germany in the 1950s. In 1953, he participated in two German-based non-championship races using a privately entered Veritas. He also raced in the 1953 German Grand Prix at the Nrburgring in his privateer Veritas, but retired after 10 laps due to engine failure.", "titles_percentage": 0.0, "poles_percentage": 0.0, "wins_percentage": 0.0, "podiums_percentage": 0.0, "seasons_results": {"1953": {"title": 0, "races": 0, "wins": 0, "points": 0, "poles": 0, "podiums": 0}}}